devModel/__init__.py
devModel/core.py
devModel/eda/__init__.py
devModel/eda/core.py
devModel-0.0.1.dist-info/LICENSE
devModel-0.0.1.dist-info/METADATA
devModel-0.0.1.dist-info/WHEEL
devModel-0.0.1.dist-info/top_level.txt
devModel-0.0.1.dist-info/RECORD
