Metadata-Version: 2.1
Name: devModel
Version: 0.0.1
Summary: An useful easy_deco package for any projects
Home-page: https://github.com/crivero7/easy-deco
Author: Carlos Rivero
Author-email: cdrr.rivero@gmail.com
License: MIT
Platform: UNKNOWN
Classifier: Programming Language :: Python :: 3
Classifier: License :: OSI Approved :: MIT License
Classifier: Operating System :: OS Independent
Requires-Dist: tqdm (==4.50.2)
